{"db_id": "store_product", "db_path": "spider::store_product::Db", "classes": {"spider::store_product::model::default::Product": {"simple_name": "Product", "properties": [{"name": "productId", "type": {"kind": "primitive", "name": "String"}, "mult": {"lower": 0, "upper": 1}}, {"name": "product", "type": {"kind": "primitive", "name": "String"}, "mult": {"lower": 0, "upper": 1}}, {"name": "dimensions", "type": {"kind": "primitive", "name": "String"}, "mult": {"lower": 0, "upper": 1}}, {"name": "dpi", "type": {"kind": "primitive", "name": "String"}, "mult": {"lower": 0, "upper": 1}}, {"name": "pagesPerMinuteColor", "type": {"kind": "primitive", "name": "String"}, "mult": {"lower": 0, "upper": 1}}, {"name": "maxPageSize", "type": {"kind": "primitive", "name": "String"}, "mult": {"lower": 0, "upper": 1}}, {"name": "interface", "type": {"kind": "primitive", "name": "String"}, "mult": {"lower": 0, "upper": 1}}], "qualified_properties": [], "super_types": []}, "spider::store_product::model::default::Store": {"simple_name": "Store", "properties": [{"name": "storeId", "type": {"kind": "primitive", "name": "String"}, "mult": {"lower": 0, "upper": 1}}, {"name": "storeName", "type": {"kind": "primitive", "name": "String"}, "mult": {"lower": 0, "upper": 1}}, {"name": "type", "type": {"kind": "primitive", "name": "String"}, "mult": {"lower": 0, "upper": 1}}, {"name": "areaSize", "type": {"kind": "primitive", "name": "String"}, "mult": {"lower": 0, "upper": 1}}, {"name": "numberOfProductCategory", "type": {"kind": "primitive", "name": "String"}, "mult": {"lower": 0, "upper": 1}}, {"name": "ranking", "type": {"kind": "primitive", "name": "String"}, "mult": {"lower": 0, "upper": 1}}], "qualified_properties": [], "super_types": []}, "spider::store_product::model::default::District": {"simple_name": "District", "properties": [{"name": "districtId", "type": {"kind": "primitive", "name": "String"}, "mult": {"lower": 0, "upper": 1}}, {"name": "districtName", "type": {"kind": "primitive", "name": "String"}, "mult": {"lower": 0, "upper": 1}}, {"name": "headquarteredCity", "type": {"kind": "primitive", "name": "String"}, "mult": {"lower": 0, "upper": 1}}, {"name": "cityPopulation", "type": {"kind": "primitive", "name": "String"}, "mult": {"lower": 0, "upper": 1}}, {"name": "cityArea", "type": {"kind": "primitive", "name": "String"}, "mult": {"lower": 0, "upper": 1}}], "qualified_properties": [], "super_types": []}, "spider::store_product::model::default::StoreProduct": {"simple_name": "StoreProduct", "properties": [{"name": "storeId", "type": {"kind": "primitive", "name": "String"}, "mult": {"lower": 0, "upper": 1}}, {"name": "productId", "type": {"kind": "primitive", "name": "String"}, "mult": {"lower": 0, "upper": 1}}], "qualified_properties": [], "super_types": []}, "spider::store_product::model::default::StoreDistrict": {"simple_name": "StoreDistrict", "properties": [{"name": "storeId", "type": {"kind": "primitive", "name": "String"}, "mult": {"lower": 0, "upper": 1}}, {"name": "districtId", "type": {"kind": "primitive", "name": "String"}, "mult": {"lower": 0, "upper": 1}}], "qualified_properties": [], "super_types": []}}, "associations": [{"path": "spider::store_product::model::fk_0", "ends": [{"property_name": "storeProducts", "target_class": "spider::store_product::model::default::StoreProduct", "mult": {"lower": 0, "upper": null}}, {"property_name": "store", "target_class": "spider::store_product::model::default::Store", "mult": {"lower": 0, "upper": 1}}]}, {"path": "spider::store_product::model::fk_1", "ends": [{"property_name": "storeDistricts", "target_class": "spider::store_product::model::default::StoreDistrict", "mult": {"lower": 0, "upper": null}}, {"property_name": "district", "target_class": "spider::store_product::model::default::District", "mult": {"lower": 0, "upper": 1}}]}, {"path": "spider::store_product::model::fk_2", "ends": [{"property_name": "storeDistricts", "target_class": "spider::store_product::model::default::StoreDistrict", "mult": {"lower": 0, "upper": null}}, {"property_name": "store", "target_class": "spider::store_product::model::default::Store", "mult": {"lower": 0, "upper": 1}}]}], "enums": {}}